[
	{
		"inputs": [
			{
				"internalType": "uint256",
				"name": "_policyId",
				"type": "uint256"
			}
		],
		"name": "acceptClaim",
		"outputs": [],
		"stateMutability": "nonpayable",
		"type": "function"
	},
	{
		"inputs": [
			{
				"internalType": "address",
				"name": "_hospital",
				"type": "address"
			}
		],
		"name": "authorizeHospital",
		"outputs": [],
		"stateMutability": "nonpayable",
		"type": "function"
	},
	{
		"inputs": [
			{
				"internalType": "address",
				"name": "_didRegistryAddress",
				"type": "address"
			}
		],
		"stateMutability": "nonpayable",
		"type": "constructor"
	},
	{
		"anonymous": false,
		"inputs": [
			{
				"indexed": true,
				"internalType": "uint256",
				"name": "policyId",
				"type": "uint256"
			},
			{
				"indexed": true,
				"internalType": "address",
				"name": "holder",
				"type": "address"
			},
			{
				"indexed": false,
				"internalType": "uint256",
				"name": "claimAmt",
				"type": "uint256"
			}
		],
		"name": "ClaimAccepted",
		"type": "event"
	},
	{
		"anonymous": false,
		"inputs": [
			{
				"indexed": true,
				"internalType": "uint256",
				"name": "policyId",
				"type": "uint256"
			},
			{
				"indexed": true,
				"internalType": "address",
				"name": "holder",
				"type": "address"
			},
			{
				"indexed": false,
				"internalType": "uint256",
				"name": "claimAmt",
				"type": "uint256"
			}
		],
		"name": "ClaimMade",
		"type": "event"
	},
	{
		"anonymous": false,
		"inputs": [
			{
				"indexed": true,
				"internalType": "uint256",
				"name": "policyId",
				"type": "uint256"
			},
			{
				"indexed": true,
				"internalType": "address",
				"name": "holder",
				"type": "address"
			}
		],
		"name": "ClaimRejected",
		"type": "event"
	},
	{
		"anonymous": false,
		"inputs": [
			{
				"indexed": true,
				"internalType": "address",
				"name": "claimSettlementAddress",
				"type": "address"
			}
		],
		"name": "ClaimSettlementContractSet",
		"type": "event"
	},
	{
		"inputs": [
			{
				"internalType": "string",
				"name": "_did",
				"type": "string"
			},
			{
				"internalType": "string",
				"name": "_insuranceCompanyName",
				"type": "string"
			},
			{
				"internalType": "string",
				"name": "_hospitalName",
				"type": "string"
			},
			{
				"internalType": "uint256",
				"name": "_amount",
				"type": "uint256"
			},
			{
				"internalType": "uint256",
				"name": "_premium",
				"type": "uint256"
			},
			{
				"internalType": "uint256",
				"name": "_startDate",
				"type": "uint256"
			},
			{
				"internalType": "uint256",
				"name": "_endDate",
				"type": "uint256"
			}
		],
		"name": "createIns",
		"outputs": [
			{
				"internalType": "uint256",
				"name": "",
				"type": "uint256"
			}
		],
		"stateMutability": "nonpayable",
		"type": "function"
	},
	{
		"inputs": [
			{
				"internalType": "string",
				"name": "_did",
				"type": "string"
			},
			{
				"internalType": "uint256",
				"name": "_amount",
				"type": "uint256"
			},
			{
				"internalType": "uint256",
				"name": "_premium",
				"type": "uint256"
			},
			{
				"internalType": "uint256",
				"name": "_endDate",
				"type": "uint256"
			}
		],
		"name": "createPolicy",
		"outputs": [
			{
				"internalType": "uint256",
				"name": "",
				"type": "uint256"
			}
		],
		"stateMutability": "nonpayable",
		"type": "function"
	},
	{
		"inputs": [
			{
				"internalType": "address",
				"name": "_hospital",
				"type": "address"
			}
		],
		"name": "deauthorizeHospital",
		"outputs": [],
		"stateMutability": "nonpayable",
		"type": "function"
	},
	{
		"anonymous": false,
		"inputs": [
			{
				"indexed": true,
				"internalType": "address",
				"name": "hospital",
				"type": "address"
			}
		],
		"name": "HospitalAuthorized",
		"type": "event"
	},
	{
		"anonymous": false,
		"inputs": [
			{
				"indexed": true,
				"internalType": "address",
				"name": "hospital",
				"type": "address"
			}
		],
		"name": "HospitalDeauthorized",
		"type": "event"
	},
	{
		"inputs": [
			{
				"internalType": "uint256",
				"name": "_policyId",
				"type": "uint256"
			},
			{
				"internalType": "uint256",
				"name": "_claimAmt",
				"type": "uint256"
			}
		],
		"name": "makeClaim",
		"outputs": [],
		"stateMutability": "nonpayable",
		"type": "function"
	},
	{
		"anonymous": false,
		"inputs": [
			{
				"indexed": true,
				"internalType": "address",
				"name": "holder",
				"type": "address"
			},
			{
				"indexed": true,
				"internalType": "uint256",
				"name": "policyId",
				"type": "uint256"
			},
			{
				"indexed": false,
				"internalType": "uint256",
				"name": "startDate",
				"type": "uint256"
			},
			{
				"indexed": false,
				"internalType": "uint256",
				"name": "endDate",
				"type": "uint256"
			}
		],
		"name": "PolicyCreated",
		"type": "event"
	},
	{
		"anonymous": false,
		"inputs": [
			{
				"indexed": true,
				"internalType": "uint256",
				"name": "policyId",
				"type": "uint256"
			},
			{
				"indexed": true,
				"internalType": "address",
				"name": "hospital",
				"type": "address"
			},
			{
				"indexed": false,
				"internalType": "string",
				"name": "procedureName",
				"type": "string"
			}
		],
		"name": "ProcedureRecorded",
		"type": "event"
	},
	{
		"inputs": [
			{
				"internalType": "uint256",
				"name": "_policyId",
				"type": "uint256"
			},
			{
				"internalType": "string",
				"name": "_name",
				"type": "string"
			}
		],
		"name": "recordProcedure",
		"outputs": [],
		"stateMutability": "nonpayable",
		"type": "function"
	},
	{
		"inputs": [
			{
				"internalType": "uint256",
				"name": "_policyId",
				"type": "uint256"
			}
		],
		"name": "rejectClaim",
		"outputs": [],
		"stateMutability": "nonpayable",
		"type": "function"
	},
	{
		"inputs": [
			{
				"internalType": "address",
				"name": "_claimSettlementAddress",
				"type": "address"
			}
		],
		"name": "setClaimSettlementContract",
		"outputs": [],
		"stateMutability": "nonpayable",
		"type": "function"
	},
	{
		"inputs": [
			{
				"internalType": "address",
				"name": "_insuranceCompany",
				"type": "address"
			}
		],
		"name": "setInsuranceCompany",
		"outputs": [],
		"stateMutability": "nonpayable",
		"type": "function"
	},
	{
		"stateMutability": "payable",
		"type": "receive"
	},
	{
		"inputs": [],
		"name": "admin",
		"outputs": [
			{
				"internalType": "address",
				"name": "",
				"type": "address"
			}
		],
		"stateMutability": "view",
		"type": "function"
	},
	{
		"inputs": [
			{
				"internalType": "address",
				"name": "",
				"type": "address"
			}
		],
		"name": "authorizedHospitals",
		"outputs": [
			{
				"internalType": "bool",
				"name": "",
				"type": "bool"
			}
		],
		"stateMutability": "view",
		"type": "function"
	},
	{
		"inputs": [
			{
				"internalType": "address",
				"name": "",
				"type": "address"
			}
		],
		"name": "claimHistory",
		"outputs": [
			{
				"internalType": "uint256",
				"name": "",
				"type": "uint256"
			}
		],
		"stateMutability": "view",
		"type": "function"
	},
	{
		"inputs": [],
		"name": "claimSettlement",
		"outputs": [
			{
				"internalType": "contract ClaimSettlement",
				"name": "",
				"type": "address"
			}
		],
		"stateMutability": "view",
		"type": "function"
	},
	{
		"inputs": [],
		"name": "didRegistry",
		"outputs": [
			{
				"internalType": "contract DIDregister",
				"name": "",
				"type": "address"
			}
		],
		"stateMutability": "view",
		"type": "function"
	},
	{
		"inputs": [
			{
				"internalType": "uint256",
				"name": "_policyId",
				"type": "uint256"
			}
		],
		"name": "getPolicyDetails",
		"outputs": [
			{
				"internalType": "address",
				"name": "holder",
				"type": "address"
			},
			{
				"internalType": "uint256",
				"name": "amount",
				"type": "uint256"
			},
			{
				"internalType": "uint256",
				"name": "premium",
				"type": "uint256"
			},
			{
				"internalType": "uint256",
				"name": "startDate",
				"type": "uint256"
			},
			{
				"internalType": "uint256",
				"name": "endDate",
				"type": "uint256"
			},
			{
				"internalType": "enum Insurance.PolicyStatus",
				"name": "status",
				"type": "uint8"
			},
			{
				"internalType": "string",
				"name": "holderDID",
				"type": "string"
			},
			{
				"internalType": "string",
				"name": "insuranceCompanyName",
				"type": "string"
			},
			{
				"internalType": "string",
				"name": "hospitalName",
				"type": "string"
			}
		],
		"stateMutability": "view",
		"type": "function"
	},
	{
		"inputs": [
			{
				"internalType": "uint256",
				"name": "_policyId",
				"type": "uint256"
			}
		],
		"name": "getPolicyStatus",
		"outputs": [
			{
				"internalType": "enum Insurance.PolicyStatus",
				"name": "",
				"type": "uint8"
			}
		],
		"stateMutability": "view",
		"type": "function"
	},
	{
		"inputs": [
			{
				"internalType": "uint256",
				"name": "_policyId",
				"type": "uint256"
			}
		],
		"name": "getProcedures",
		"outputs": [
			{
				"components": [
					{
						"internalType": "string",
						"name": "name",
						"type": "string"
					},
					{
						"internalType": "uint256",
						"name": "timestamp",
						"type": "uint256"
					},
					{
						"internalType": "bool",
						"name": "verified",
						"type": "bool"
					},
					{
						"internalType": "address",
						"name": "hospital",
						"type": "address"
					}
				],
				"internalType": "struct Insurance.Procedure[]",
				"name": "",
				"type": "tuple[]"
			}
		],
		"stateMutability": "view",
		"type": "function"
	},
	{
		"inputs": [
			{
				"internalType": "address",
				"name": "_user",
				"type": "address"
			}
		],
		"name": "getUserPolicies",
		"outputs": [
			{
				"internalType": "uint256[]",
				"name": "",
				"type": "uint256[]"
			}
		],
		"stateMutability": "view",
		"type": "function"
	},
	{
		"inputs": [],
		"name": "insuranceCompany",
		"outputs": [
			{
				"internalType": "address",
				"name": "",
				"type": "address"
			}
		],
		"stateMutability": "view",
		"type": "function"
	},
	{
		"inputs": [
			{
				"internalType": "uint256",
				"name": "",
				"type": "uint256"
			}
		],
		"name": "policies",
		"outputs": [
			{
				"internalType": "address",
				"name": "holder",
				"type": "address"
			},
			{
				"internalType": "uint256",
				"name": "amount",
				"type": "uint256"
			},
			{
				"internalType": "uint256",
				"name": "premium",
				"type": "uint256"
			},
			{
				"internalType": "uint256",
				"name": "startDate",
				"type": "uint256"
			},
			{
				"internalType": "uint256",
				"name": "endDate",
				"type": "uint256"
			},
			{
				"internalType": "enum Insurance.PolicyStatus",
				"name": "status",
				"type": "uint8"
			},
			{
				"internalType": "string",
				"name": "holderDID",
				"type": "string"
			},
			{
				"internalType": "string",
				"name": "insuranceCompanyName",
				"type": "string"
			},
			{
				"internalType": "string",
				"name": "hospitalName",
				"type": "string"
			}
		],
		"stateMutability": "view",
		"type": "function"
	},
	{
		"inputs": [
			{
				"internalType": "uint256",
				"name": "",
				"type": "uint256"
			},
			{
				"internalType": "uint256",
				"name": "",
				"type": "uint256"
			}
		],
		"name": "policyProcedures",
		"outputs": [
			{
				"internalType": "string",
				"name": "name",
				"type": "string"
			},
			{
				"internalType": "uint256",
				"name": "timestamp",
				"type": "uint256"
			},
			{
				"internalType": "bool",
				"name": "verified",
				"type": "bool"
			},
			{
				"internalType": "address",
				"name": "hospital",
				"type": "address"
			}
		],
		"stateMutability": "view",
		"type": "function"
	},
	{
		"inputs": [
			{
				"internalType": "address",
				"name": "",
				"type": "address"
			},
			{
				"internalType": "uint256",
				"name": "",
				"type": "uint256"
			}
		],
		"name": "userPolicies",
		"outputs": [
			{
				"internalType": "uint256",
				"name": "",
				"type": "uint256"
			}
		],
		"stateMutability": "view",
		"type": "function"
	}
]